castor/__init__.py
castor/cli.py
castor/core.py
castor/server.py
castor/ui.py
castor_io-0.7.0.dist-info/METADATA
castor_io-0.7.0.dist-info/WHEEL
castor_io-0.7.0.dist-info/entry_points.txt
castor_io-0.7.0.dist-info/RECORD
