Metadata-Version: 2.4
Name: castor-io
Version: 0.7.0
Summary: Minimalistic, embedded task manager.
Author-email: Alejandro Piad <apiad@apiad.net>
Classifier: License :: OSI Approved :: MIT License
Classifier: Operating System :: OS Independent
Classifier: Programming Language :: Python :: 3.13
Classifier: Topic :: Database
Classifier: Topic :: Software Development :: Libraries :: Application Frameworks
Requires-Python: >=3.13
Requires-Dist: beaver-db>=1.0.0
Requires-Dist: typer>=0.19.2
